modernlab/__init__.py
modernlab/quick_plot.py
modernlab/variational_error.py
modernlab-0.1.1.dist-info/LICENSE.txt
modernlab-0.1.1.dist-info/METADATA
modernlab-0.1.1.dist-info/WHEEL
modernlab-0.1.1.dist-info/top_level.txt
modernlab-0.1.1.dist-info/RECORD
