Metadata-Version: 2.1
Name: modernlab
Version: 0.1.1
Summary: Data visualization and analysis toolst
Home-page: https://github.com/AlexZades/modernlab
Author: Alex Zades
Author-email: az@st4r.io
License: UNKNOWN
Project-URL: Wiki, https://github.com/AlexZades/modernlab/wiki
Platform: UNKNOWN
Requires-Python: >=3.5
Requires-Dist: numpy
Requires-Dist: scipy
